Metadata-Version: 2.4
Name: traceroot-framework
Version: 0.1.1
Summary: TraceRoot - Comprehensive AI-powered tracing, monitoring and REST API solution
Author: Zecheng Zhang, Xinwei He
License: Apache-2.0
Project-URL: Homepage, https://github.com/traceroot-ai/traceroot
Project-URL: Documentation, https://github.com/traceroot-ai/traceroot#readme
Project-URL: Repository, https://github.com/traceroot-ai/traceroot
Project-URL: Bug Reports, https://github.com/traceroot-ai/traceroot/issues
Keywords: opentelemetry,agents,dev,del-tools,artificial-intelligence,tracing,logging,debugging,rest-api,multi-agent-systems,coding,debugging-assistant
Classifier: Development Status :: 3 - Alpha
Classifier: Intended Audience :: Developers
Classifier: License :: OSI Approved :: Apache Software License
Classifier: Programming Language :: Python :: 3
Classifier: Programming Language :: Python :: 3.8
Classifier: Programming Language :: Python :: 3.9
Classifier: Programming Language :: Python :: 3.10
Classifier: Programming Language :: Python :: 3.11
Classifier: Programming Language :: Python :: 3.12
Classifier: Topic :: Software Development :: Libraries :: Python Modules
Classifier: Topic :: System :: Logging
Classifier: Topic :: System :: Monitoring
Classifier: Topic :: Internet :: WWW/HTTP :: HTTP Servers
Requires-Python: >=3.10
License-File: LICENSE
Requires-Dist: fastapi==0.116.1
Requires-Dist: uvicorn==0.35.0
Requires-Dist: httpx==0.28.1
Requires-Dist: pyjwt==2.10.1
Requires-Dist: cryptography==45.0.5
Requires-Dist: python-jose[cryptography]==3.5.0
Requires-Dist: python-multipart==0.0.20
Requires-Dist: requests==2.32.4
Requires-Dist: openai==1.99.2
Requires-Dist: pymongo==4.13.2
Requires-Dist: boto3==1.39.11
Requires-Dist: numpy==2.2.0
Requires-Dist: asgiref==3.9.1
Requires-Dist: slowapi==0.1.9
Requires-Dist: aiocache==0.12.3
Requires-Dist: PyGithub==2.6.1
Requires-Dist: pydantic==2.11.7
Requires-Dist: python-dotenv==1.1.1
Requires-Dist: pydantic-settings==2.10.1
Requires-Dist: dotenv==0.9.9
Requires-Dist: traceroot==0.0.4a9
Requires-Dist: aiosqlite==0.21.0
Requires-Dist: stripe==12.3.0
Requires-Dist: docstring_parser==0.17.0
Requires-Dist: autumn-py==2.2.2
Requires-Dist: aiohttp==3.12.15
Requires-Dist: groq==0.11.0
Provides-Extra: dev
Requires-Dist: pytest==8.4.1; extra == "dev"
Requires-Dist: pytest-asyncio==1.1.0; extra == "dev"
Requires-Dist: black==25.1.0; extra == "dev"
Requires-Dist: flake8==7.3.0; extra == "dev"
Requires-Dist: ruff==0.12.4; extra == "dev"
Requires-Dist: mypy==1.17.0; extra == "dev"
Requires-Dist: pre-commit==4.2.0; extra == "dev"
Provides-Extra: all
Requires-Dist: fastapi==0.116.1; extra == "all"
Requires-Dist: uvicorn==0.35.0; extra == "all"
Requires-Dist: httpx==0.28.1; extra == "all"
Requires-Dist: pyjwt==2.10.1; extra == "all"
Requires-Dist: cryptography==45.0.5; extra == "all"
Requires-Dist: python-jose[cryptography]==3.5.0; extra == "all"
Requires-Dist: python-multipart==0.0.20; extra == "all"
Requires-Dist: requests==2.32.4; extra == "all"
Requires-Dist: openai==1.99.2; extra == "all"
Requires-Dist: pymongo==4.13.2; extra == "all"
Requires-Dist: boto3==1.39.11; extra == "all"
Requires-Dist: numpy==2.2.0; extra == "all"
Requires-Dist: asgiref==3.9.1; extra == "all"
Requires-Dist: slowapi==0.1.9; extra == "all"
Requires-Dist: aiocache==0.12.3; extra == "all"
Requires-Dist: PyGithub==2.6.1; extra == "all"
Requires-Dist: pydantic==2.11.7; extra == "all"
Requires-Dist: python-dotenv==1.1.1; extra == "all"
Requires-Dist: pydantic-settings==2.10.1; extra == "all"
Requires-Dist: dotenv==0.9.9; extra == "all"
Requires-Dist: traceroot==0.0.4a9; extra == "all"
Requires-Dist: aiosqlite==0.21.0; extra == "all"
Requires-Dist: stripe==12.3.0; extra == "all"
Requires-Dist: docstring_parser==0.17.0; extra == "all"
Requires-Dist: pytest==8.4.1; extra == "all"
Requires-Dist: pytest-asyncio==1.1.0; extra == "all"
Requires-Dist: black==25.1.0; extra == "all"
Requires-Dist: flake8==7.3.0; extra == "all"
Requires-Dist: ruff==0.12.4; extra == "all"
Requires-Dist: mypy==1.17.0; extra == "all"
Requires-Dist: pre-commit==4.2.0; extra == "all"
Requires-Dist: aiohttp==3.12.15; extra == "all"
Requires-Dist: groq==0.11.0; extra == "all"
Dynamic: license-file
